README.md
doc/momos_header.svg
momos/__init__.py
momos/cli.py
momos/components/__init__.py
momos/components/basic.py
momos/components/mode.py
momos/components/trigger.py
momos/generator.py
momos/graph.py
momos/libraries/gtest/momos.hpp
momos/parser/__init__.py
momos/parser/grammar.lark
momos/parser/parse.py
momos/suite.py
momos/templates/gtest/suite.j2
momos/utils.py
momos-1.0.1.dist-info/entry_points.txt
momos-1.0.1.dist-info/WHEEL
momos-1.0.1.dist-info/METADATA
momos-1.0.1.dist-info/RECORD
